aiida_phtools/__init__.py
aiida_phtools/calculations/__init__.py
aiida_phtools/calculations/distance_matrix.py
aiida_phtools/calculations/pore_surface.py
aiida_phtools/calculations/test_distance_matrix.py
aiida_phtools/calculations/test_pore_surface.py
aiida_phtools/data/__init__.py
aiida_phtools/data/data_cli.py
aiida_phtools/data/pore_surface.py
aiida_phtools/parsers/__init__.py
aiida_phtools/parsers/distance_matrix.py
aiida_phtools/parsers/pore_surface.py
aiida_phtools/tests/__init__.py
aiida_phtools/workflows/__init__.py
aiida_phtools/workflows/dmatrix.py
aiida_phtools/workflows/test_dmatrix.py
aiida_phtools-0.1.0a1.data/scripts/cli.py
aiida_phtools-0.1.0a1.dist-info/METADATA
aiida_phtools-0.1.0a1.dist-info/RECORD
aiida_phtools-0.1.0a1.dist-info/WHEEL
aiida_phtools-0.1.0a1.dist-info/entry_points.txt
aiida_phtools-0.1.0a1.dist-info/top_level.txt
